dynoptimdict/__init__.py
dynoptimdict/dynamic_dict.py
dynoptimdict-2.0.0.dist-info/LICENSE
dynoptimdict-2.0.0.dist-info/METADATA
dynoptimdict-2.0.0.dist-info/WHEEL
dynoptimdict-2.0.0.dist-info/RECORD
