Metadata-Version: 2.1
Name: dynoptimdict
Version: 2.0.0
Summary: A dynamic dict class that inherits and overrides the built-in dict class for special purposes. That provides real-time access to dynamic data, while still allowing the option to get only the specified data without calculating all. It adheres to the concept of program optimization which avoids loading if not used, saving both memory and time.
Home-page: https://github.com/leoweyr/Python-Dynoptimdict
License: MIT
Author: leoweyr
Author-email: leoweyr@foxmail.com
Requires-Python: >=3.8,<4.0
Classifier: Development Status :: 4 - Beta
Classifier: License :: OSI Approved :: MIT License
Classifier: Programming Language :: Python :: 3
Classifier: Programming Language :: Python :: 3.8
Classifier: Programming Language :: Python :: 3.9
Classifier: Programming Language :: Python :: 3.10
Classifier: Programming Language :: Python :: 3.11
Project-URL: Repository, https://github.com/leoweyr/Python-Dynoptimdict
